chat2webdav/__init__.py
chat2webdav/chat.py
chat2webdav/cli.py
chat2webdav/config.py
chat2webdav/sync_client.py
chat2webdav/webdav.py
chat2webdav/llm/__init__.py
chat2webdav/llm/base.py
chat2webdav-0.1.0.dist-info/METADATA
chat2webdav-0.1.0.dist-info/WHEEL
chat2webdav-0.1.0.dist-info/entry_points.txt
chat2webdav-0.1.0.dist-info/licenses/LICENSE
chat2webdav-0.1.0.dist-info/RECORD
